{
  "song_id": 114,
  "name": "Heaven Help The Fool",
  "performances": [
    {
      "votes": 12,
      "date": "1980-10-31",
      "show_id": 961,
      "venue": "Radio City Music Hall New York, NY",
      "description": "Wish I would have seen it with the Dead",
      "archive_url": "https://headyversion.com/show/961/archive/"
    },
    {
      "votes": 10,
      "date": "1980-10-10",
      "show_id": 145,
      "venue": "Warfield Theater San Francisco, CA",
      "description": "Absolutely a fantastic song, should have been played more. nice acoustic jam",
      "archive_url": "https://headyversion.com/show/145/archive/"
    },
    {
      "votes": 7,
      "date": "1994-09-24",
      "show_id": 1276,
      "venue": "Berkeley Community Theatre Berkeley, CA",
      "description": "phil and friends show small venue great accoustic show",
      "archive_url": "https://headyversion.com/show/1276/archive/"
    },
    {
      "votes": 6,
      "date": "1980-10-14",
      "show_id": 531,
      "venue": "Warfield Theater San Francisco, CA",
      "description": "Sweet Acoustic Jam",
      "archive_url": "https://headyversion.com/show/531/archive/"
    },
    {
      "votes": 6,
      "date": "1980-10-11",
      "show_id": 963,
      "venue": "Warfield Theater San Francisco, CA",
      "description": "another stellar acoustic treat",
      "archive_url": "https://headyversion.com/show/963/archive/"
    },
    {
      "votes": 5,
      "date": "1980-10-30",
      "show_id": 90,
      "venue": "Radio City Music Hall New York, NY",
      "description": "fantastic acoustic instrumental jam, song has lyrics they just did not sing them acoustically",
      "archive_url": "https://headyversion.com/show/90/archive/"
    },
    {
      "votes": 3,
      "date": "1980-10-29",
      "show_id": 1160,
      "venue": "Radio City Music Hall New York, NY",
      "description": "another amazing workout of this gem",
      "archive_url": "https://headyversion.com/show/1160/archive/"
    },
    {
      "votes": 3,
      "date": "1980-10-27",
      "show_id": 959,
      "venue": "Radio City Music Hall New York, NY",
      "description": "Killer acoustic jam",
      "archive_url": "https://headyversion.com/show/959/archive/"
    },
    {
      "votes": 3,
      "date": "1980-10-03",
      "show_id": 964,
      "venue": "Warfield Theater San Francisco, CA",
      "description": "sweet tune",
      "archive_url": "https://headyversion.com/show/964/archive/"
    },
    {
      "votes": 3,
      "date": "1980-09-30",
      "show_id": 547,
      "venue": "Warfield Theatre San Francisco, CA",
      "description": "second time played",
      "archive_url": "https://headyversion.com/show/547/archive/"
    },
    {
      "votes": 3,
      "date": "1980-10-18",
      "show_id": 1792,
      "venue": "Saenger Performing Arts Center New Orleans, LA",
      "description": "acoustic jam love it",
      "archive_url": "https://headyversion.com/show/1792/archive/"
    },
    {
      "votes": 3,
      "date": "1980-10-13",
      "show_id": 949,
      "venue": "Warfield Theater San Francisco, CA",
      "description": "A special one just for you, Wonderful acoustic gem, played with a special extra zeal on this evening. Near flawless performance.",
      "archive_url": "https://headyversion.com/show/949/archive/"
    },
    {
      "votes": 2,
      "date": "1980-10-25",
      "show_id": 1067,
      "venue": "Radio City Music Hall New York, NY",
      "description": "Hot, just listen to this one love the intricate acoustic jam.",
      "archive_url": "https://headyversion.com/show/1067/archive/"
    },
    {
      "votes": 2,
      "date": "1980-10-07",
      "show_id": 1100,
      "venue": "Warfield Theater San Francisco, CA",
      "description": "Another acoustic jam beauty, special times.",
      "archive_url": "https://headyversion.com/show/1100/archive/"
    },
    {
      "votes": 2,
      "date": "1980-10-22",
      "show_id": 1791,
      "venue": "Radio City Music Hall New York, NY",
      "description": "heady heaven help the fool, bird song->Ripple",
      "archive_url": "https://headyversion.com/show/1791/archive/"
    },
    {
      "votes": 2,
      "date": "1980-09-29",
      "show_id": 1774,
      "venue": "Warfield Theater San Francisco, CA",
      "description": "First time played absolutely a gem",
      "archive_url": "https://headyversion.com/show/1774/archive/"
    },
    {
      "votes": 1,
      "date": "1980-10-06",
      "show_id": 1779,
      "venue": "Warfield Theater San Francisco, CA",
      "description": "this i such a sweet tune performed excellently on this night",
      "archive_url": "https://headyversion.com/show/1779/archive/"
    }
  ]
}