{
  "song_id": 216,
  "name": "Ramble On Rose",
  "performances": [
    {
      "votes": 88,
      "date": "1989-07-07",
      "show_id": 281,
      "venue": "JFK Stadium Philadelphia, PA",
      "description": "",
      "archive_url": "https://headyversion.com/show/281/archive/"
    },
    {
      "votes": 66,
      "date": "1978-12-31",
      "show_id": 356,
      "venue": "Winterland Arena San Francisco, CA",
      "description": "Do I hear angels? Yep, Jerry's at it again.",
      "archive_url": "https://headyversion.com/show/356/archive/"
    },
    {
      "votes": 60,
      "date": "1978-04-24",
      "show_id": 72,
      "venue": "Horton Field House - Illinois State University Normal, IL",
      "description": "A cool version from a great show.",
      "archive_url": "https://headyversion.com/show/72/archive/"
    },
    {
      "votes": 58,
      "date": "1973-11-11",
      "show_id": 434,
      "venue": "Winterland Arena San Francisco, CA",
      "description": "Beautiful tender version.  Jerry is spectacular!",
      "archive_url": "https://headyversion.com/show/434/archive/"
    },
    {
      "votes": 51,
      "date": "1972-05-25",
      "show_id": 401,
      "venue": "Strand Lyceum London, UK",
      "description": "Yet another great '72 version.",
      "archive_url": "https://headyversion.com/show/401/archive/"
    },
    {
      "votes": 47,
      "date": "1980-11-30",
      "show_id": 36,
      "venue": "Fox Theatre Atlanta, GA",
      "description": "Jerry sounds \"just like Wolfman Jack\" when he growwwlllzzz out the final chorus on \"Goodbye Mama & Papa...!\" Whole version is aces back to back!",
      "archive_url": "https://headyversion.com/show/36/archive/"
    },
    {
      "votes": 42,
      "date": "1977-05-19",
      "show_id": 244,
      "venue": "Fox Theatre Atlanta, GA",
      "description": "Gorgeous, incredible, up and down, carnival-like bridge jam by Jerry. Picture perfect version--no flaws",
      "archive_url": "https://headyversion.com/show/244/archive/"
    },
    {
      "votes": 41,
      "date": "1972-05-26",
      "show_id": 575,
      "venue": "Strand Lyceum London,",
      "description": "Normally bored by this song, but this shines",
      "archive_url": "https://headyversion.com/show/575/archive/"
    },
    {
      "votes": 36,
      "date": "1976-10-10",
      "show_id": 746,
      "venue": "Oakland-Alameda County Coliseum Oakland, CA",
      "description": "DP33 version.  Jerry coming unglued at the end. Energy!",
      "archive_url": "https://headyversion.com/show/746/archive/"
    },
    {
      "votes": 36,
      "date": "1972-09-21",
      "show_id": 142,
      "venue": "The Spectrum Philadelphia, PA",
      "description": "Band in full attack mode. Picture perfect dynamics.",
      "archive_url": "https://headyversion.com/show/142/archive/"
    },
    {
      "votes": 36,
      "date": "1978-07-08",
      "show_id": 427,
      "venue": "Red Rocks Amphitheatre Morrison, CO",
      "description": "Conjures circus tents, smoky saloons and Frankenstein in a souped-up '57 Chevy. Well worth a listen!",
      "archive_url": "https://headyversion.com/show/427/archive/"
    },
    {
      "votes": 31,
      "date": "1990-03-29",
      "show_id": 188,
      "venue": "Nassau Coliseum Uniondale, NY",
      "description": "",
      "archive_url": "https://headyversion.com/show/188/archive/"
    },
    {
      "votes": 29,
      "date": "1976-09-25",
      "show_id": 649,
      "venue": "Capital Centre Landover, MD",
      "description": "Dick's Picks 20 version",
      "archive_url": "https://headyversion.com/show/649/archive/"
    },
    {
      "votes": 29,
      "date": "1972-09-27",
      "show_id": 583,
      "venue": "Stanley Theatre Jersey City, NJ",
      "description": "Jerry's vocals and the energy. Wow.",
      "archive_url": "https://headyversion.com/show/583/archive/"
    },
    {
      "votes": 27,
      "date": "1977-05-22",
      "show_id": 100,
      "venue": "The Sportatorium Pembroke Pines, FL",
      "description": "Just discovered this one, available on archive as outtakes that didn't make the DP release. Simply put, it kicks ass.",
      "archive_url": "https://headyversion.com/show/100/archive/"
    },
    {
      "votes": 26,
      "date": "1973-11-17",
      "show_id": 430,
      "venue": "Pauley Pavilion - University of California Los Angeles, CA",
      "description": "I really can't believe no one has submitted this show. Ethereal playing. Stunning sound quality. Start at \"Me & My Uncle\" and don't stop, trust me..",
      "archive_url": "https://headyversion.com/show/430/archive/"
    },
    {
      "votes": 25,
      "date": "1972-05-07",
      "show_id": 445,
      "venue": "Bickershaw Festival Wigan,",
      "description": "Great Europe '72 version",
      "archive_url": "https://headyversion.com/show/445/archive/"
    },
    {
      "votes": 24,
      "date": "1973-12-19",
      "show_id": 442,
      "venue": "Curtis Hixon Convention Hall Tampa, FL",
      "description": "",
      "archive_url": "https://headyversion.com/show/442/archive/"
    },
    {
      "votes": 24,
      "date": "1989-10-09",
      "show_id": 318,
      "venue": "Hampton Coliseum Hampton, VA",
      "description": "",
      "archive_url": "https://headyversion.com/show/318/archive/"
    },
    {
      "votes": 23,
      "date": "1990-09-20",
      "show_id": 354,
      "venue": "Madison Square Garden New York, NY",
      "description": "Wow, just wow",
      "archive_url": "https://headyversion.com/show/354/archive/"
    },
    {
      "votes": 22,
      "date": "1977-10-29",
      "show_id": 525,
      "venue": "Evans Field House, Northern Illinois University Dekalb, Il",
      "description": "Epic, energetic version!",
      "archive_url": "https://headyversion.com/show/525/archive/"
    },
    {
      "votes": 21,
      "date": "1974-06-23",
      "show_id": 92,
      "venue": "Jai-Alai Fronton Miami, FL",
      "description": "",
      "archive_url": "https://headyversion.com/show/92/archive/"
    },
    {
      "votes": 21,
      "date": "1990-10-27",
      "show_id": 1313,
      "venue": "The Zenith Paris,",
      "description": "Szechuan Jerry...he's all sweet and hot on this one from the 30 Trips box. Spicy!",
      "archive_url": "https://headyversion.com/show/1313/archive/"
    },
    {
      "votes": 20,
      "date": "1985-04-27",
      "show_id": 298,
      "venue": "Frost Amphitheatre Palo Alto, CA",
      "description": "Growling jerry, and so much going on in the background of this tune on this night. Phil and Brent are doing some wild things as is Bobby. Very HOT",
      "archive_url": "https://headyversion.com/show/298/archive/"
    },
    {
      "votes": 19,
      "date": "1977-11-02",
      "show_id": 859,
      "venue": "Field House - Seneca College Toronto, ON",
      "description": "Excellent reading of this classic!",
      "archive_url": "https://headyversion.com/show/859/archive/"
    },
    {
      "votes": 18,
      "date": "1973-03-26",
      "show_id": 509,
      "venue": "Baltimore Civic Center Baltimore, MD",
      "description": "Wolfman Jack himself introed this pretty good version at a decidly under rated show,gotta be some props for that .",
      "archive_url": "https://headyversion.com/show/509/archive/"
    },
    {
      "votes": 17,
      "date": "1974-06-18",
      "show_id": 97,
      "venue": "Freedom Hall Louisville, KY",
      "description": "Perfect",
      "archive_url": "https://headyversion.com/show/97/archive/"
    },
    {
      "votes": 17,
      "date": "1972-04-07",
      "show_id": 1070,
      "venue": "Wembley Empire Pool London,",
      "description": "This one cuts like it should. Forceful, churning, and tight.",
      "archive_url": "https://headyversion.com/show/1070/archive/"
    },
    {
      "votes": 17,
      "date": "1973-12-02",
      "show_id": 428,
      "venue": "Music Hall Boston, MA",
      "description": "",
      "archive_url": "https://headyversion.com/show/428/archive/"
    },
    {
      "votes": 15,
      "date": "1977-04-23",
      "show_id": 172,
      "venue": "Springfield Civic Center Springfield, MA",
      "description": "",
      "archive_url": "https://headyversion.com/show/172/archive/"
    },
    {
      "votes": 15,
      "date": "1972-04-11",
      "show_id": 528,
      "venue": "Newcastle City Hall Newcastle,",
      "description": "Hot, with Jerry going all-out--",
      "archive_url": "https://headyversion.com/show/528/archive/"
    },
    {
      "votes": 15,
      "date": "1972-05-03",
      "show_id": 80,
      "venue": "Olympia Theater Paris,",
      "description": "Another great '72 version",
      "archive_url": "https://headyversion.com/show/80/archive/"
    },
    {
      "votes": 14,
      "date": "1977-03-20",
      "show_id": 89,
      "venue": "Winterland Arena San Francisco, CA",
      "description": "Majestic, Jerry and keith are truly spot on for this pairing, Crisp beautiful version on Archive.",
      "archive_url": "https://headyversion.com/show/89/archive/"
    },
    {
      "votes": 13,
      "date": "1984-07-15",
      "show_id": 139,
      "venue": "Greek Theatre - University of California Berkeley, CA",
      "description": "My all time favorite show, every song from Dancin' to the double encore SMOKES even better then the 13th!!!!",
      "archive_url": "https://headyversion.com/show/139/archive/"
    },
    {
      "votes": 13,
      "date": "1972-05-04",
      "show_id": 549,
      "venue": "Olympia Theater Paris,",
      "description": "Heady set 2 version",
      "archive_url": "https://headyversion.com/show/549/archive/"
    },
    {
      "votes": 13,
      "date": "1973-06-10",
      "show_id": 144,
      "venue": "RFK Stadium Washington, DC",
      "description": "Fantastic following the Morning Dew opener, this one is rocking and rolling and has me dancing like a fool. Great stuff.",
      "archive_url": "https://headyversion.com/show/144/archive/"
    },
    {
      "votes": 13,
      "date": "1981-03-09",
      "show_id": 82,
      "venue": "Madison Square Garden New York City, NY",
      "description": "",
      "archive_url": "https://headyversion.com/show/82/archive/"
    },
    {
      "votes": 13,
      "date": "1973-04-02",
      "show_id": 50,
      "venue": "Boston Garden Boston, MA",
      "description": "Lovely, like everything in this epic show.",
      "archive_url": "https://headyversion.com/show/50/archive/"
    },
    {
      "votes": 13,
      "date": "1974-05-17",
      "show_id": 771,
      "venue": "P.N.E. Coliseum Vancouver, BC",
      "description": "Not my favorite tune, but nice swing to this one.",
      "archive_url": "https://headyversion.com/show/771/archive/"
    },
    {
      "votes": 12,
      "date": "1993-09-22",
      "show_id": 234,
      "venue": "Madison Square Garden New York, NY",
      "description": "how is this NOT listed?? a sterling example of Garcia's quirky melodic sensibilities. the solo is crafted with care and nice MIDI layering",
      "archive_url": "https://headyversion.com/show/234/archive/"
    },
    {
      "votes": 11,
      "date": "1971-12-09",
      "show_id": 1164,
      "venue": "Fox Theatre St. Louis, MO",
      "description": "",
      "archive_url": "https://headyversion.com/show/1164/archive/"
    },
    {
      "votes": 11,
      "date": "1974-07-31",
      "show_id": 568,
      "venue": "Dillon Stadium Hartford, CT",
      "description": "Jerry is in his element.",
      "archive_url": "https://headyversion.com/show/568/archive/"
    },
    {
      "votes": 11,
      "date": "1994-10-14",
      "show_id": 1079,
      "venue": "Madison Square Garden New York, NY",
      "description": "\"Just like NYC\"",
      "archive_url": "https://headyversion.com/show/1079/archive/"
    },
    {
      "votes": 11,
      "date": "1983-10-12",
      "show_id": 775,
      "venue": "Madison Square Garden New York, NY",
      "description": "The audience lights up when Jerry sings \"just like New York City\"",
      "archive_url": "https://headyversion.com/show/775/archive/"
    },
    {
      "votes": 11,
      "date": "1972-04-14",
      "show_id": 135,
      "venue": "Tivolis Koncertsal Copenhagen, DN",
      "description": "Jer: \"This is a new song... and it goes exactly like this\".  Pigpen: \"No it don't.\" Either way, it kicks like the good stuff.",
      "archive_url": "https://headyversion.com/show/135/archive/"
    },
    {
      "votes": 11,
      "date": "1977-05-11",
      "show_id": 585,
      "venue": "St. Paul Civic Center Arena St. Paul, MN",
      "description": "perfect version at this most perfect show",
      "archive_url": "https://headyversion.com/show/585/archive/"
    },
    {
      "votes": 11,
      "date": "1978-07-03",
      "show_id": 1749,
      "venue": "St. Paul Civic Center Arena St. Paul, MN",
      "description": "Tight, inspired, and growling by Jer.",
      "archive_url": "https://headyversion.com/show/1749/archive/"
    },
    {
      "votes": 11,
      "date": "1971-11-17",
      "show_id": 1542,
      "venue": "Albuquerque Civic Auditorium Albuquerque, NM",
      "description": "Pretty unique as an encore",
      "archive_url": "https://headyversion.com/show/1542/archive/"
    },
    {
      "votes": 10,
      "date": "1973-10-30",
      "show_id": 468,
      "venue": "Kiel Auditorium St. Louis, MO",
      "description": "Very nice...unlike any version Ive listened to...just sweet, and Jerry actually nailed the lyrics!!!",
      "archive_url": "https://headyversion.com/show/468/archive/"
    },
    {
      "votes": 10,
      "date": "1972-05-18",
      "show_id": 290,
      "venue": "Kongressaal, Deutsches Museum Munich, DE",
      "description": "Band bristles with restrained energy.  Jerry's voice is scratchy and perfect.  Great harmony on the chorus.",
      "archive_url": "https://headyversion.com/show/290/archive/"
    },
    {
      "votes": 10,
      "date": "1977-06-08",
      "show_id": 439,
      "venue": "Winterland Arena San Francisco, CA",
      "description": "6/7 and 6/9 get all the attention, show more love for this one",
      "archive_url": "https://headyversion.com/show/439/archive/"
    },
    {
      "votes": 10,
      "date": "1972-04-17",
      "show_id": 399,
      "venue": "Tivolis Koncertsal K\u00f8benhavn (Copenhagen),",
      "description": "Europe set 2 version",
      "archive_url": "https://headyversion.com/show/399/archive/"
    },
    {
      "votes": 10,
      "date": "1982-07-31",
      "show_id": 464,
      "venue": "Manor Downs Austin, TX",
      "description": "Hot version from a stellar show",
      "archive_url": "https://headyversion.com/show/464/archive/"
    },
    {
      "votes": 10,
      "date": "1972-11-19",
      "show_id": 459,
      "venue": "Hofheinz Pavilion Houston, TX",
      "description": "Absolutely stunning Jerry vocals, beautifully sung.",
      "archive_url": "https://headyversion.com/show/459/archive/"
    },
    {
      "votes": 10,
      "date": "1971-11-15",
      "show_id": 446,
      "venue": "The Austin Municipal Auditorium Austin, TX",
      "description": "Always a fun song. This gets lost in a great show. Jerry is on start to finish",
      "archive_url": "https://headyversion.com/show/446/archive/"
    },
    {
      "votes": 9,
      "date": "1977-05-13",
      "show_id": 451,
      "venue": "Auditorium Theatre Chicago, IL",
      "description": "rollicking, great pace, just works!",
      "archive_url": "https://headyversion.com/show/451/archive/"
    },
    {
      "votes": 9,
      "date": "1989-06-21",
      "show_id": 199,
      "venue": "Shoreline Amphitheatre Mountain View, CA",
      "description": "",
      "archive_url": "https://headyversion.com/show/199/archive/"
    },
    {
      "votes": 9,
      "date": "1972-05-10",
      "show_id": 745,
      "venue": "Concertgebouw Amsterdam,",
      "description": "Another classic Europe '72 version.",
      "archive_url": "https://headyversion.com/show/745/archive/"
    },
    {
      "votes": 9,
      "date": "1993-06-06",
      "show_id": 265,
      "venue": "Giants Stadium East Rutherford, NJ",
      "description": "great late era version of this classic tune.",
      "archive_url": "https://headyversion.com/show/265/archive/"
    },
    {
      "votes": 9,
      "date": "1973-12-06",
      "show_id": 19,
      "venue": "Public Hall Cleveland, OH",
      "description": "Really? Why is this not on here?",
      "archive_url": "https://headyversion.com/show/19/archive/"
    },
    {
      "votes": 9,
      "date": "1982-08-07",
      "show_id": 573,
      "venue": "Alpine Valley Music Theatre East Troy, WI",
      "description": "Crisp and popping. Gorgeous show DP 32",
      "archive_url": "https://headyversion.com/show/573/archive/"
    },
    {
      "votes": 9,
      "date": "1978-02-01",
      "show_id": 1151,
      "venue": "Uptown Theatre Chicago, IL",
      "description": "Excellent 78 Ramble on Rose...",
      "archive_url": "https://headyversion.com/show/1151/archive/"
    },
    {
      "votes": 8,
      "date": "1983-04-13",
      "show_id": 463,
      "venue": "Patrick Gymnasium, U of Vermont Burlington, VT",
      "description": "Brent's modulation is wacky and goes right with this version....wierd but good",
      "archive_url": "https://headyversion.com/show/463/archive/"
    },
    {
      "votes": 8,
      "date": "1971-12-05",
      "show_id": 791,
      "venue": "Felt Forum - Madison Square Garden New York, NY",
      "description": "Great version",
      "archive_url": "https://headyversion.com/show/791/archive/"
    },
    {
      "votes": 8,
      "date": "1987-07-12",
      "show_id": 166,
      "venue": "Giants Stadium East Rutherford, NJ",
      "description": "",
      "archive_url": "https://headyversion.com/show/166/archive/"
    },
    {
      "votes": 8,
      "date": "1972-05-23",
      "show_id": 400,
      "venue": "Strand Lyceum London, UK",
      "description": "Try to walk the linee",
      "archive_url": "https://headyversion.com/show/400/archive/"
    },
    {
      "votes": 8,
      "date": "1993-01-26",
      "show_id": 1562,
      "venue": "Oakland-Alameda County Coliseum Arena Oakland, CA",
      "description": "Jerry relys heavy Heavy on the MIDI but RIPPING solos and Vince again shines brightly this whole run",
      "archive_url": "https://headyversion.com/show/1562/archive/"
    },
    {
      "votes": 8,
      "date": "1979-12-03",
      "show_id": 1083,
      "venue": "Uptown Theatre Chicago, IL",
      "description": "Excellent late 1979 version. Nice Brent fills.",
      "archive_url": "https://headyversion.com/show/1083/archive/"
    },
    {
      "votes": 8,
      "date": "1977-10-07",
      "show_id": 890,
      "venue": "University of New Mexico Albuquerque, NM",
      "description": "Brilliant, tough recording, CM has a partial up including this beauty",
      "archive_url": "https://headyversion.com/show/890/archive/"
    },
    {
      "votes": 8,
      "date": "1978-10-21",
      "show_id": 155,
      "venue": "Winterland Arena San Francisco, CA",
      "description": "Terriffic from the Egypt with love shows",
      "archive_url": "https://headyversion.com/show/155/archive/"
    },
    {
      "votes": 8,
      "date": "1990-03-18",
      "show_id": 1024,
      "venue": "Civic Center Hartford, CT",
      "description": "Fantastic late era Brent version, been really groovin on this tune lately.",
      "archive_url": "https://headyversion.com/show/1024/archive/"
    },
    {
      "votes": 8,
      "date": "1979-12-30",
      "show_id": 710,
      "venue": "Oakland Auditorium Oakland, CA",
      "description": "Nice pace and vocals, almost as rockin' as the (pinnacle) '78 versions, with some Brent keys thrown in.",
      "archive_url": "https://headyversion.com/show/710/archive/"
    },
    {
      "votes": 8,
      "date": "1973-12-08",
      "show_id": 660,
      "venue": "Cameron Indoor Stadium, Duke U Durham, NC",
      "description": "A very tight version with great Phil bombs and Jerry solo. This show slips under the radar. Don't miss it.",
      "archive_url": "https://headyversion.com/show/660/archive/"
    },
    {
      "votes": 7,
      "date": "1981-09-26",
      "show_id": 632,
      "venue": "Buffalo Auditorium Buffalo, NY",
      "description": "Jerry's first solo puts this one over the top",
      "archive_url": "https://headyversion.com/show/632/archive/"
    },
    {
      "votes": 7,
      "date": "1971-12-31",
      "show_id": 409,
      "venue": "Winterland Arena San Francisco, CA",
      "description": "Cool New Years version",
      "archive_url": "https://headyversion.com/show/409/archive/"
    },
    {
      "votes": 7,
      "date": "1979-10-31",
      "show_id": 447,
      "venue": "Nassau Coliseum Uniondale, NY",
      "description": "great jerry/brent interplay",
      "archive_url": "https://headyversion.com/show/447/archive/"
    },
    {
      "votes": 7,
      "date": "1977-05-01",
      "show_id": 179,
      "venue": "The Palladium New York, NY",
      "description": "the crowd in the aud is worth it. the recation when jerry sings \"just like new york city\" no wonder they always loved nyc",
      "archive_url": "https://headyversion.com/show/179/archive/"
    },
    {
      "votes": 7,
      "date": "1984-07-22",
      "show_id": 429,
      "venue": "Ventura County Fairgrounds Ventura, CA",
      "description": "Whole show has that extra bouncy punch to it. Jerry has the 84 growl going on big time.",
      "archive_url": "https://headyversion.com/show/429/archive/"
    },
    {
      "votes": 7,
      "date": "1991-06-09",
      "show_id": 227,
      "venue": "Buckeye Lake Music Center Hebron, OH",
      "description": "Very nicely performed Ramble on Rose.",
      "archive_url": "https://headyversion.com/show/227/archive/"
    },
    {
      "votes": 7,
      "date": "1993-09-17",
      "show_id": 1751,
      "venue": "Madison Square Garden New York, NY",
      "description": "Just like New York City....",
      "archive_url": "https://headyversion.com/show/1751/archive/"
    },
    {
      "votes": 7,
      "date": "1972-09-15",
      "show_id": 1889,
      "venue": "Boston Music Hall Boston, MA",
      "description": "Jerry's vocals are rarely stronger.  At one point he's growling it out like he's spittin' nails.",
      "archive_url": "https://headyversion.com/show/1889/archive/"
    },
    {
      "votes": 7,
      "date": "1990-07-14",
      "show_id": 1750,
      "venue": "Foxboro Stadium Foxboro, MA",
      "description": "This version rewards multiple listens. Like it was good the first time, great the second. I hesitate to listen to it again. Bobby leads the way.",
      "archive_url": "https://headyversion.com/show/1750/archive/"
    },
    {
      "votes": 7,
      "date": "1973-09-08",
      "show_id": 804,
      "venue": "Nassau Coliseum Uniondale, NY",
      "description": "Jerry and Bob are both really good on this one. Phil and Bill drive it forward nicely as well -- doesn't drag at all like some do.",
      "archive_url": "https://headyversion.com/show/804/archive/"
    },
    {
      "votes": 6,
      "date": "1971-10-19",
      "show_id": 513,
      "venue": "Northrop Auditorium, U. of Minn. Minneapolis, MN",
      "description": "First time played on Keiths first night.  Very raw and experimental but still absolutely rockin!!",
      "archive_url": "https://headyversion.com/show/513/archive/"
    },
    {
      "votes": 6,
      "date": "1974-07-27",
      "show_id": 1042,
      "venue": "Civic Center Roanoke, VA",
      "description": "This has a grat bounce to it and Keith is playing an electric piano so it sounds differnt than his usual grand. Jerry Rips a wonderful solo, HOT vers.",
      "archive_url": "https://headyversion.com/show/1042/archive/"
    },
    {
      "votes": 6,
      "date": "1995-05-21",
      "show_id": 116,
      "venue": "Sam Boyd Silver Bowl Las Vegas, NV",
      "description": "",
      "archive_url": "https://headyversion.com/show/116/archive/"
    },
    {
      "votes": 6,
      "date": "1973-03-16",
      "show_id": 363,
      "venue": "Nassau Coliseum Uniondale, NY",
      "description": "",
      "archive_url": "https://headyversion.com/show/363/archive/"
    },
    {
      "votes": 6,
      "date": "1977-04-27",
      "show_id": 24,
      "venue": "Capitol Theatre Passaic, NJ",
      "description": "Sweet '77 version!",
      "archive_url": "https://headyversion.com/show/24/archive/"
    },
    {
      "votes": 6,
      "date": "1993-05-26",
      "show_id": 207,
      "venue": "Cal Expo Sacramento, CA",
      "description": "Definitely the best show of the year.  Great tight version at this perfect show.",
      "archive_url": "https://headyversion.com/show/207/archive/"
    },
    {
      "votes": 6,
      "date": "1993-09-10",
      "show_id": 232,
      "venue": "Richfield Coliseum Richfield, OH",
      "description": "A very spunky, sharp and well played version with Jerry on fire. He owns this whole first set.",
      "archive_url": "https://headyversion.com/show/232/archive/"
    },
    {
      "votes": 6,
      "date": "1972-09-28",
      "show_id": 41,
      "venue": "Stanley Theatre Jersey City, NJ",
      "description": "Much like the Philly version a week earlier, this one really shines.",
      "archive_url": "https://headyversion.com/show/41/archive/"
    },
    {
      "votes": 6,
      "date": "1978-05-10",
      "show_id": 532,
      "venue": "Veterans' Memorial Coliseum New Haven, CT",
      "description": "Dick's 25 ...",
      "archive_url": "https://headyversion.com/show/532/archive/"
    },
    {
      "votes": 6,
      "date": "1974-02-23",
      "show_id": 360,
      "venue": "Winterland Arena San Francisco, CA",
      "description": "Can't believe it's not listed.",
      "archive_url": "https://headyversion.com/show/360/archive/"
    },
    {
      "votes": 5,
      "date": "1983-09-08",
      "show_id": 462,
      "venue": "Red Rocks Morrison, CO",
      "description": "once it gets rolling you can't beat the emotion",
      "archive_url": "https://headyversion.com/show/462/archive/"
    },
    {
      "votes": 5,
      "date": "1980-12-13",
      "show_id": 1073,
      "venue": "Long Beach Arena Long Beach, CA",
      "description": "A fantastic version from a fantastic show!",
      "archive_url": "https://headyversion.com/show/1073/archive/"
    },
    {
      "votes": 5,
      "date": "1972-08-22",
      "show_id": 1361,
      "venue": "Berkeley Community Theatre Berkeley, CA",
      "description": "Another '72 version played with purpose and conviction. Dynamite playing by everyone.",
      "archive_url": "https://headyversion.com/show/1361/archive/"
    },
    {
      "votes": 5,
      "date": "1973-02-09",
      "show_id": 99,
      "venue": "Roscoe Maples Pavilion - Stanford University Palo Alto, CA",
      "description": "Jerry sings his heart out and hits all the right notes! Awesome version!",
      "archive_url": "https://headyversion.com/show/99/archive/"
    },
    {
      "votes": 5,
      "date": "1971-10-26",
      "show_id": 1413,
      "venue": "The Palestra, U. of Rochester Rochester, NY",
      "description": "One of the earliest live versions ever and boy oh boy is Jerry into it. Belts out the lyrics. Quick tempo & a real joy to hear!",
      "archive_url": "https://headyversion.com/show/1413/archive/"
    },
    {
      "votes": 5,
      "date": "1979-01-11",
      "show_id": 31,
      "venue": "Nassau Coliseum Uniondale, NY",
      "description": "\u201cRose\u201d has that nice shuffle-boogie I love so much (I think they nail the tempo). Listen to the crowd explode when he hits the \u201cjust like NYC\u201d line!",
      "archive_url": "https://headyversion.com/show/31/archive/"
    },
    {
      "votes": 5,
      "date": "1977-09-29",
      "show_id": 1249,
      "venue": "Paramount Theatre Seattle, WA",
      "description": "",
      "archive_url": "https://headyversion.com/show/1249/archive/"
    },
    {
      "votes": 5,
      "date": "1972-07-26",
      "show_id": 1018,
      "venue": "Paramount Theater Portland, OR",
      "description": "Tremendous early Keith era version, tremendous",
      "archive_url": "https://headyversion.com/show/1018/archive/"
    },
    {
      "votes": 5,
      "date": "1985-06-28",
      "show_id": 238,
      "venue": "Hershey Park Stadium Hershey, PA",
      "description": "Tremendous show in Chocolate town USA Hershey PA",
      "archive_url": "https://headyversion.com/show/238/archive/"
    },
    {
      "votes": 5,
      "date": "1983-10-21",
      "show_id": 706,
      "venue": "Worcester Centrum Worcester, MA",
      "description": "Another stand out from another very hot early 80's show",
      "archive_url": "https://headyversion.com/show/706/archive/"
    },
    {
      "votes": 5,
      "date": "1984-10-20",
      "show_id": 94,
      "venue": "Carrier Dome, Syracuse U Syracuse, NY",
      "description": "Jerry's voice is a little raspy, standard 1984, but this version has a sweet bounce to it and Boobys backing and brent's keys just lift this to great",
      "archive_url": "https://headyversion.com/show/94/archive/"
    },
    {
      "votes": 5,
      "date": "1984-04-29",
      "show_id": 2031,
      "venue": "Nassau Coliseum Uniondale, NY",
      "description": "Incredibly mellow spacey reading definetly a Persian Jerry show, has that hazy spaciness to it very fine performance.",
      "archive_url": "https://headyversion.com/show/2031/archive/"
    },
    {
      "votes": 5,
      "date": "1978-04-21",
      "show_id": 648,
      "venue": "Rupp Arena Lexington, KY",
      "description": "Weir sticking with slide on this one, Garcia and gang rip through the solo and after!",
      "archive_url": "https://headyversion.com/show/648/archive/"
    },
    {
      "votes": 5,
      "date": "1972-03-23",
      "show_id": 1262,
      "venue": "Academy of Music New York, NY",
      "description": "The whole band collectively slams this one home",
      "archive_url": "https://headyversion.com/show/1262/archive/"
    },
    {
      "votes": 5,
      "date": "1992-06-22",
      "show_id": 1030,
      "venue": "Star Lake Amphitheater Burgettstown, PA",
      "description": "A great ragtimey version!",
      "archive_url": "https://headyversion.com/show/1030/archive/"
    },
    {
      "votes": 5,
      "date": "1971-12-07",
      "show_id": 16,
      "venue": "Felt Forum, Madison Square Garden New York, NY",
      "description": "Not my favorite tune, but the 71 grove got me interested.",
      "archive_url": "https://headyversion.com/show/16/archive/"
    },
    {
      "votes": 5,
      "date": "1972-08-21",
      "show_id": 1122,
      "venue": "Berkeley Community Theater Berkeley, CA",
      "description": "Emphatic.",
      "archive_url": "https://headyversion.com/show/1122/archive/"
    },
    {
      "votes": 5,
      "date": "1971-10-22",
      "show_id": 1332,
      "venue": "Auditorium Theatre Chicago, IL",
      "description": "Fresh!",
      "archive_url": "https://headyversion.com/show/1332/archive/"
    },
    {
      "votes": 5,
      "date": "1994-09-29",
      "show_id": 366,
      "venue": "Boston Garden Boston, MA",
      "description": "Shockingly good. Only good things to say about the Boston Garden run from this tour. These first few nights allayed fears after awful summer tour.",
      "archive_url": "https://headyversion.com/show/366/archive/"
    },
    {
      "votes": 5,
      "date": "1974-08-05",
      "show_id": 517,
      "venue": "Philadelphia Civic Arena Philadelphia, PA",
      "description": "",
      "archive_url": "https://headyversion.com/show/517/archive/"
    },
    {
      "votes": 4,
      "date": "1972-01-02",
      "show_id": 42,
      "venue": "Winterland Arena San Francisco, CA",
      "description": "Good energy on this version per usual in 'frisco.",
      "archive_url": "https://headyversion.com/show/42/archive/"
    },
    {
      "votes": 4,
      "date": "1973-06-30",
      "show_id": 133,
      "venue": "Universal Amphitheatre Universal City, CA",
      "description": "AUD is preferable here. Lesh-heavy. Weir's work is outstanding. Billy and Keith hammer away g",
      "archive_url": "https://headyversion.com/show/133/archive/"
    },
    {
      "votes": 4,
      "date": "1983-05-15",
      "show_id": 869,
      "venue": "Greek Theatre - University of California Berkeley, CA",
      "description": "Very tastefully done",
      "archive_url": "https://headyversion.com/show/869/archive/"
    },
    {
      "votes": 4,
      "date": "1973-07-31",
      "show_id": 1311,
      "venue": "Roosevelt Stadium Jersey City, NJ",
      "description": "Crowd pumped up for this 1st set opener.  Juiced and tight.  Starts one hell of show.",
      "archive_url": "https://headyversion.com/show/1311/archive/"
    },
    {
      "votes": 4,
      "date": "1973-09-12",
      "show_id": 1297,
      "venue": "William and Mary College Hall Williamsburg, VA",
      "description": "Impassioned version like few others, with both Jer and Keith firing on all cylinders. Terrible AUD probs keep this show unknown, but worth a listen.",
      "archive_url": "https://headyversion.com/show/1297/archive/"
    },
    {
      "votes": 4,
      "date": "1977-12-30",
      "show_id": 636,
      "venue": "Winterland Arena San Francisco, CA",
      "description": "Faster than usual tempo with just a brilliant Jerry bridge jam and no missed lyrics make this one a not-to-be-missed version.",
      "archive_url": "https://headyversion.com/show/636/archive/"
    },
    {
      "votes": 4,
      "date": "1971-10-30",
      "show_id": 1343,
      "venue": "Taft Auditorium Cincinnati, OH",
      "description": "Not my favorite song, but this one rocks. Plus Jerry eviscerates a heckler after.",
      "archive_url": "https://headyversion.com/show/1343/archive/"
    },
    {
      "votes": 4,
      "date": "1978-12-12",
      "show_id": 1670,
      "venue": "Jai-Alai Fronton Miami, FL",
      "description": "Wow terriffic, blistering Jerry guitar work nice phil runs and keys are there, Jerry really has the axe singing on this one.",
      "archive_url": "https://headyversion.com/show/1670/archive/"
    },
    {
      "votes": 4,
      "date": "1982-12-31",
      "show_id": 754,
      "venue": "Oakland Auditorium Oakland, CA",
      "description": "jerry freakin on it. wonderful version!!",
      "archive_url": "https://headyversion.com/show/754/archive/"
    },
    {
      "votes": 4,
      "date": "1984-04-06",
      "show_id": 1456,
      "venue": "Aladdin Theater Las Vegas, NV",
      "description": "aggressive playing from Brent",
      "archive_url": "https://headyversion.com/show/1456/archive/"
    },
    {
      "votes": 4,
      "date": "1987-03-31",
      "show_id": 994,
      "venue": "The Spectrum Philadelphia, PA",
      "description": "Not spectacular but as solid as they come!",
      "archive_url": "https://headyversion.com/show/994/archive/"
    },
    {
      "votes": 4,
      "date": "1972-11-24",
      "show_id": 850,
      "venue": "Dallas Memorial Auditorium Dallas, TX",
      "description": "Hard rocking version from a tight 2nd set.",
      "archive_url": "https://headyversion.com/show/850/archive/"
    },
    {
      "votes": 4,
      "date": "1971-10-21",
      "show_id": 397,
      "venue": "Auditorium Theatre Chicago, IL",
      "description": "Keith's second show & he's all over this faster paced super fun honky tonk version!",
      "archive_url": "https://headyversion.com/show/397/archive/"
    },
    {
      "votes": 4,
      "date": "1972-09-03",
      "show_id": 664,
      "venue": "Folsom Field, University of Colorado Boulder, CO",
      "description": "Collectively nail this with some X-factor swing and swagger.",
      "archive_url": "https://headyversion.com/show/664/archive/"
    },
    {
      "votes": 4,
      "date": "1981-12-05",
      "show_id": 76,
      "venue": "Market Square Arena Indianapolis, IN",
      "description": "Crisp Vocals. Great show. Worth a listen.",
      "archive_url": "https://headyversion.com/show/76/archive/"
    },
    {
      "votes": 4,
      "date": "1993-03-10",
      "show_id": 307,
      "venue": "Rosemont Horizon Rosemont, IL",
      "description": "Jer sounds excellent vocally here -band fills in the gaps nicely -spring tour 93 is very nice mellow dead :)",
      "archive_url": "https://headyversion.com/show/307/archive/"
    },
    {
      "votes": 4,
      "date": "1972-07-22",
      "show_id": 1407,
      "venue": "Paramount Northwest Theatre Seattle, WA",
      "description": "Heat Miser hot",
      "archive_url": "https://headyversion.com/show/1407/archive/"
    },
    {
      "votes": 4,
      "date": "1972-10-17",
      "show_id": 498,
      "venue": "Fox Theatre St. Louis, MO",
      "description": "Love Keith\u2019s flourishes here. Great version with perfect vocals",
      "archive_url": "https://headyversion.com/show/498/archive/"
    },
    {
      "votes": 3,
      "date": "1992-06-25",
      "show_id": 306,
      "venue": "Soldier Field Chicago, IL",
      "description": "my favorite version, jerry takes this one over the top during the jam",
      "archive_url": "https://headyversion.com/show/306/archive/"
    },
    {
      "votes": 3,
      "date": "1981-03-02",
      "show_id": 668,
      "venue": "Cleveland Music Hall Cleveland, OH",
      "description": "",
      "archive_url": "https://headyversion.com/show/668/archive/"
    },
    {
      "votes": 3,
      "date": "1972-08-12",
      "show_id": 823,
      "venue": "Sacramento Memorial Auditorium Sacramento, CA",
      "description": "Do yourself a favor! Give this version a listen. It's the fire and verve.",
      "archive_url": "https://headyversion.com/show/823/archive/"
    },
    {
      "votes": 3,
      "date": "1971-11-12",
      "show_id": 1571,
      "venue": "San Antonio Civic Auditorium San Antonio, TX",
      "description": "Solid and strong. Keith's sound is way high in the mix, but to nice effect.  Unfortunately jerry is  barely audible.  Could use a fix.",
      "archive_url": "https://headyversion.com/show/1571/archive/"
    },
    {
      "votes": 3,
      "date": "1981-10-12",
      "show_id": 824,
      "venue": "Olympia Halle Munich,",
      "description": "Love this tune, solid version diggin jerrys voice in this one",
      "archive_url": "https://headyversion.com/show/824/archive/"
    },
    {
      "votes": 3,
      "date": "1981-12-30",
      "show_id": 2006,
      "venue": "Oakland Auditorium Oakland, CA",
      "description": "Sweet set 3. Excellent R.O.R. follows a stranger that was performed sans Brent.",
      "archive_url": "https://headyversion.com/show/2006/archive/"
    },
    {
      "votes": 3,
      "date": "1990-02-26",
      "show_id": 812,
      "venue": "Oakland-Alameda County Coliseum Arena Oakland, CA",
      "description": "Beautiful version hot tight and sweet",
      "archive_url": "https://headyversion.com/show/812/archive/"
    },
    {
      "votes": 3,
      "date": "1995-06-27",
      "show_id": 273,
      "venue": "The Palace Auburn Hills, MI",
      "description": "",
      "archive_url": "https://headyversion.com/show/273/archive/"
    },
    {
      "votes": 3,
      "date": "1985-10-28",
      "show_id": 884,
      "venue": "Fox Theater Atlanta, GA",
      "description": "Garcia and his fretboard are truly one with vocal rage taboot. I find this to be a favorite 80s first set of mine.",
      "archive_url": "https://headyversion.com/show/884/archive/"
    },
    {
      "votes": 3,
      "date": "1991-03-28",
      "show_id": 698,
      "venue": "Nassau Coliseum Uniondale, NY",
      "description": "standout from a short but crisp first set.",
      "archive_url": "https://headyversion.com/show/698/archive/"
    },
    {
      "votes": 3,
      "date": "1971-10-27",
      "show_id": 1420,
      "venue": "Onondaga War Memorial Syracuse, NY",
      "description": "Extremely aggressive version, this is good stuff.",
      "archive_url": "https://headyversion.com/show/1420/archive/"
    },
    {
      "votes": 3,
      "date": "1979-10-28",
      "show_id": 1096,
      "venue": "Cape Cod Coliseum South Yarmouth, MA",
      "description": "The jam is both melodic and surging. A great taste of the early 80's sound",
      "archive_url": "https://headyversion.com/show/1096/archive/"
    },
    {
      "votes": 3,
      "date": "1980-05-08",
      "show_id": 1402,
      "venue": "Glens Falls Civic Center Glens Falls, NY",
      "description": "Magic",
      "archive_url": "https://headyversion.com/show/1402/archive/"
    },
    {
      "votes": 3,
      "date": "1972-03-21",
      "show_id": 391,
      "venue": "Academy of Music New York City, NY",
      "description": "Crisp tight version sung beautifully , outstanding mix and everyone has standout moments. Nice Phi backing up Jerry, and Keith shines brightly thru ou",
      "archive_url": "https://headyversion.com/show/391/archive/"
    },
    {
      "votes": 3,
      "date": "1984-10-31",
      "show_id": 1782,
      "venue": "Berkley Community Theatre Berkeley, CA",
      "description": "Rousing vocal performance from Jerry",
      "archive_url": "https://headyversion.com/show/1782/archive/"
    },
    {
      "votes": 3,
      "date": "1972-07-16",
      "show_id": 74,
      "venue": "Dillon Stadium Hartford, CT",
      "description": "KEITH is on F#C&ING FIRE!!!!",
      "archive_url": "https://headyversion.com/show/74/archive/"
    },
    {
      "votes": 3,
      "date": "1991-06-19",
      "show_id": 251,
      "venue": "Pine Knob Clarkston, MI",
      "description": "",
      "archive_url": "https://headyversion.com/show/251/archive/"
    },
    {
      "votes": 3,
      "date": "1972-11-22",
      "show_id": 1455,
      "venue": "Austin Municipal Auditorium Austin, TX",
      "description": "This Rose has that saucy swagger you seek.",
      "archive_url": "https://headyversion.com/show/1455/archive/"
    },
    {
      "votes": 3,
      "date": "1971-12-06",
      "show_id": 1544,
      "venue": "Felt Forum, Madison Square Garden New York, NY",
      "description": "Similar to next night.  Cool 71 groove.",
      "archive_url": "https://headyversion.com/show/1544/archive/"
    },
    {
      "votes": 3,
      "date": "1981-03-23",
      "show_id": 1499,
      "venue": "Rainbow Theatre London,",
      "description": "",
      "archive_url": "https://headyversion.com/show/1499/archive/"
    },
    {
      "votes": 3,
      "date": "1971-10-29",
      "show_id": 1696,
      "venue": "Allen Theatre Cleveland, OH",
      "description": "One of the early bouncy ones... NYC/ Jericho part inherits new interpretation 30yrs later",
      "archive_url": "https://headyversion.com/show/1696/archive/"
    },
    {
      "votes": 3,
      "date": "1989-08-06",
      "show_id": 988,
      "venue": "Cal Expo Sacramento, CA",
      "description": "1989 was a banner year for this song. Brent is on fire and Jerry is, well, Jerry. Killer version.",
      "archive_url": "https://headyversion.com/show/988/archive/"
    },
    {
      "votes": 3,
      "date": "1980-10-31",
      "show_id": 961,
      "venue": "Radio City Music Hall New York, NY",
      "description": "It's \"ROR,\" It's NYC, 'Nuff Said.",
      "archive_url": "https://headyversion.com/show/961/archive/"
    },
    {
      "votes": 3,
      "date": "1990-09-14",
      "show_id": 1448,
      "venue": "Madison Square Garden New York, NY",
      "description": "Fun NYC version...9/20 is better, though.",
      "archive_url": "https://headyversion.com/show/1448/archive/"
    },
    {
      "votes": 3,
      "date": "1973-10-23",
      "show_id": 651,
      "venue": "Metropolitan Sports Center Bloomington, MN",
      "description": "Sharp, delightful version. Supercharged Keith\u2019s melodic lines will keep you guessing.",
      "archive_url": "https://headyversion.com/show/651/archive/"
    },
    {
      "votes": 3,
      "date": "1986-03-24",
      "show_id": 246,
      "venue": "The Spectrum Philadelphia, PA",
      "description": "Bright, peppy version from one the two or three truly great 1986 shows.",
      "archive_url": "https://headyversion.com/show/246/archive/"
    },
    {
      "votes": 2,
      "date": "1974-10-17",
      "show_id": 556,
      "venue": "Winterland Arena San Francisco, CA",
      "description": "Another knockout version of this beauty.  So delicate in this one.  Great night at Winterland as usual!",
      "archive_url": "https://headyversion.com/show/556/archive/"
    },
    {
      "votes": 2,
      "date": "1983-12-30",
      "show_id": 1336,
      "venue": "Civic Auditorium San Francisco, CA",
      "description": "Had to add this version just for the \u201cThe Grass Ain\u2019t Greener, the Wine Ain\u2019t Sweeter\u2026\u201d line. Probably the best version I saw live. Give it a listen.",
      "archive_url": "https://headyversion.com/show/1336/archive/"
    },
    {
      "votes": 2,
      "date": "1972-06-17",
      "show_id": 136,
      "venue": "Hollywood Bowl Hollywood, CA",
      "description": "Truckin'->Other One->Ramble On Rose is an awesome sequence!",
      "archive_url": "https://headyversion.com/show/136/archive/"
    },
    {
      "votes": 2,
      "date": "1986-12-27",
      "show_id": 924,
      "venue": "Henry J. Kaiser Convention Center Oakland, CA",
      "description": "",
      "archive_url": "https://headyversion.com/show/924/archive/"
    },
    {
      "votes": 2,
      "date": "1971-10-23",
      "show_id": 1426,
      "venue": "Easttown Theatre Detroit, MI",
      "description": "Solid, strident version. Bobby and Phil take on the rowdies with a cool rap after, too. Great first set all around.",
      "archive_url": "https://headyversion.com/show/1426/archive/"
    },
    {
      "votes": 2,
      "date": "1995-03-18",
      "show_id": 3,
      "venue": "The Spectrum Philadelphia, PA",
      "description": "Nice late era version of the often played classic.",
      "archive_url": "https://headyversion.com/show/3/archive/"
    },
    {
      "votes": 2,
      "date": "1972-03-27",
      "show_id": 1321,
      "venue": "Academy of Music New York, NY",
      "description": "Please listen to the whole show, go to archive find the charlie miller snbd. and listen gorgeous and as tight as 1977 dead on Europe 72 warmup",
      "archive_url": "https://headyversion.com/show/1321/archive/"
    },
    {
      "votes": 2,
      "date": "1972-10-30",
      "show_id": 1672,
      "venue": "Ford Auditorium Detroit, MI",
      "description": "A really top shelf run through of ROR. Jerry on fire vocals excellent and just rips the solos.",
      "archive_url": "https://headyversion.com/show/1672/archive/"
    },
    {
      "votes": 2,
      "date": "1995-06-19",
      "show_id": 1734,
      "venue": "Giants Stadium East Rutherford, NJ",
      "description": "",
      "archive_url": "https://headyversion.com/show/1734/archive/"
    },
    {
      "votes": 2,
      "date": "1994-10-06",
      "show_id": 1769,
      "venue": "The Spectrum Philadelphia, PA",
      "description": "",
      "archive_url": "https://headyversion.com/show/1769/archive/"
    },
    {
      "votes": 2,
      "date": "1979-01-18",
      "show_id": 1916,
      "venue": "Providence Civic Center Providence, RI",
      "description": "excellent Ramble on Rose from early 79 toward the end of the Godchaux's run with the band.",
      "archive_url": "https://headyversion.com/show/1916/archive/"
    },
    {
      "votes": 2,
      "date": "1995-02-20",
      "show_id": 1738,
      "venue": "Delta Center Salt Lake City, UT",
      "description": "",
      "archive_url": "https://headyversion.com/show/1738/archive/"
    },
    {
      "votes": 2,
      "date": "1988-03-14",
      "show_id": 2038,
      "venue": "Madison Square Garden New York, NY",
      "description": "Band feeds off the crowd. Lovely keys on this and a full-on vocal from Garcia, despite a couple of very minor flubs.",
      "archive_url": "https://headyversion.com/show/2038/archive/"
    },
    {
      "votes": 2,
      "date": "1976-10-03",
      "show_id": 562,
      "venue": "Cobo Arena Detroit, MI",
      "description": "Underrated first set here. They boys were on all night in Cobo. Jumping rose",
      "archive_url": "https://headyversion.com/show/562/archive/"
    },
    {
      "votes": 2,
      "date": "1984-04-17",
      "show_id": 1399,
      "venue": "Niagara Falls Convention Center Niagara Falls, NY",
      "description": "Really liquid lead in tremendous effort, Jerry nails it with nice inflections",
      "archive_url": "https://headyversion.com/show/1399/archive/"
    },
    {
      "votes": 2,
      "date": "1982-04-08",
      "show_id": 2007,
      "venue": "Onondaga Auditorium Syracuse, NY",
      "description": "Love Brents barroom style keyboard work.  Gives this a great old timey feel which really suits the song.",
      "archive_url": "https://headyversion.com/show/2007/archive/"
    },
    {
      "votes": 2,
      "date": "1995-06-15",
      "show_id": 1654,
      "venue": "Franklin County Airport Highgate, VT",
      "description": "Great solo, nice late version. Parasailing dude above the crowd.",
      "archive_url": "https://headyversion.com/show/1654/archive/"
    },
    {
      "votes": 2,
      "date": "1972-08-24",
      "show_id": 650,
      "venue": "Berkeley Community Theatre Berkeley, CA",
      "description": "Vocal forward - Well played, \"Good Bye Mama and Papa!\"",
      "archive_url": "https://headyversion.com/show/650/archive/"
    },
    {
      "votes": 2,
      "date": "1991-09-18",
      "show_id": 1417,
      "venue": "Madison Square Garden New York, NY",
      "description": "Last night in NYC at the Garden.",
      "archive_url": "https://headyversion.com/show/1417/archive/"
    },
    {
      "votes": 2,
      "date": "1990-12-13",
      "show_id": 1859,
      "venue": "McNichols Arena Denver, CO",
      "description": "Man was 1990 a good year for this song. Terrific version, great solo, nice ragtime-y work from Bruce. Just exactly perfect.",
      "archive_url": "https://headyversion.com/show/1859/archive/"
    },
    {
      "votes": 2,
      "date": "1991-08-16",
      "show_id": 292,
      "venue": "Shoreline Amphitheatre Mountain View, CA",
      "description": "Love this one. Spunky Jerry with a quirky, inventive solo and nice playing from Bruce as well.",
      "archive_url": "https://headyversion.com/show/292/archive/"
    },
    {
      "votes": 2,
      "date": "1972-10-27",
      "show_id": 1896,
      "venue": "Veterans' Memorial Hall Columbus, OH",
      "description": "Tis a ripper",
      "archive_url": "https://headyversion.com/show/1896/archive/"
    },
    {
      "votes": 2,
      "date": "1980-08-30",
      "show_id": 1023,
      "venue": "The Spectrum Philadelphia, PA",
      "description": "Nice version from the Spectrum",
      "archive_url": "https://headyversion.com/show/1023/archive/"
    },
    {
      "votes": 2,
      "date": "1972-12-10",
      "show_id": 750,
      "venue": "Winterland Arena San Francisco, CA",
      "description": "",
      "archive_url": "https://headyversion.com/show/750/archive/"
    },
    {
      "votes": 2,
      "date": "1971-11-20",
      "show_id": 1704,
      "venue": "Pauley Pavilion Los Angeles, CA",
      "description": "Comes out of a hot Other One. Plenty of Keith",
      "archive_url": "https://headyversion.com/show/1704/archive/"
    },
    {
      "votes": 2,
      "date": "1971-12-01",
      "show_id": 104,
      "venue": "Boston Music Hall Boston, MA",
      "description": "Keith makes this one sparkle.",
      "archive_url": "https://headyversion.com/show/104/archive/"
    },
    {
      "votes": 2,
      "date": "1984-06-30",
      "show_id": 832,
      "venue": "Indianapolis Sports and Music Center Indianapolis, IN",
      "description": "",
      "archive_url": "https://headyversion.com/show/832/archive/"
    },
    {
      "votes": 2,
      "date": "1972-11-15",
      "show_id": 423,
      "venue": "Oklahoma City Music Hall Oklahoma City, OK",
      "description": "I tend to prefer these earlier versions when it was bouncy and didn't overstay its welcome...",
      "archive_url": "https://headyversion.com/show/423/archive/"
    },
    {
      "votes": 2,
      "date": "1978-09-16",
      "show_id": 716,
      "venue": "Sphinx Theatre Giza,",
      "description": "Jerr flubs the lyrics lol",
      "archive_url": "https://headyversion.com/show/716/archive/"
    },
    {
      "votes": 2,
      "date": "1994-06-26",
      "show_id": 113,
      "venue": "Sam Boyd Silver Bowl Las Vegas, NV",
      "description": "squish lover's pizza... this one is utterly a Cezanne. essential.",
      "archive_url": "https://headyversion.com/show/113/archive/"
    },
    {
      "votes": 1,
      "date": "1985-09-10",
      "show_id": 1928,
      "venue": "Henry J. Kaiser Convention Center Oakland, CA",
      "description": "Exceptional version of a song they could sometimes put on autopilot.  not hear well intentioned and alert Jerry gets downright nasty on this version",
      "archive_url": "https://headyversion.com/show/1928/archive/"
    },
    {
      "votes": 1,
      "date": "1993-12-17",
      "show_id": 1757,
      "venue": "Oakland Coliseum Arena Oakland, CA",
      "description": "",
      "archive_url": "https://headyversion.com/show/1757/archive/"
    },
    {
      "votes": 1,
      "date": "1983-06-22",
      "show_id": 2003,
      "venue": "City Island Harrisburg, PA",
      "description": "Wonderful reading at this seldom talked about show in PA's state capital.",
      "archive_url": "https://headyversion.com/show/2003/archive/"
    },
    {
      "votes": 1,
      "date": "1981-05-15",
      "show_id": 1103,
      "venue": "Rutgers Athletic Center New Brunswick, NJ",
      "description": "A truly wonderful show underrated.",
      "archive_url": "https://headyversion.com/show/1103/archive/"
    },
    {
      "votes": 1,
      "date": "1994-12-09",
      "show_id": 1227,
      "venue": "Oakland-Alameda County Coliseum Stadium Oakland, CA",
      "description": "It may be late in the game but this is a really nice Ramble on Rose. Real nice fills from Vince",
      "archive_url": "https://headyversion.com/show/1227/archive/"
    },
    {
      "votes": 1,
      "date": "1991-04-04",
      "show_id": 342,
      "venue": "The Omni Atlanta, GA",
      "description": "MIDI orgy with special guest Bruce Horsby. It's very delifgtful/creative.",
      "archive_url": "https://headyversion.com/show/342/archive/"
    },
    {
      "votes": 1,
      "date": "1991-05-05",
      "show_id": 2000,
      "venue": "Cal Expo Sacramento, CA",
      "description": "More MIDI madness I can't get enough of it it",
      "archive_url": "https://headyversion.com/show/2000/archive/"
    },
    {
      "votes": 1,
      "date": "1991-09-12",
      "show_id": 1682,
      "venue": "Madison Square Garden New York, NY",
      "description": "They always play this one well at The Garden.",
      "archive_url": "https://headyversion.com/show/1682/archive/"
    },
    {
      "votes": 1,
      "date": "1988-09-14",
      "show_id": 1897,
      "venue": "Madison Square Garden New York, NY",
      "description": "Nice version. It was amazing to see DSO recreate this show",
      "archive_url": "https://headyversion.com/show/1897/archive/"
    },
    {
      "votes": 1,
      "date": "1989-10-01",
      "show_id": 1052,
      "venue": "Shoreline Amphitheatre Mountain View, CA",
      "description": "Another good \u201889 Ramble on Rose",
      "archive_url": "https://headyversion.com/show/1052/archive/"
    },
    {
      "votes": 1,
      "date": "1989-08-04",
      "show_id": 326,
      "venue": "Cal Expo Sacramento, CA",
      "description": "Funky, tight version with Brent especially on fire.",
      "archive_url": "https://headyversion.com/show/326/archive/"
    },
    {
      "votes": 1,
      "date": "1971-10-24",
      "show_id": 1134,
      "venue": "Easttown Theatre Detroit, MI",
      "description": "This is a clear and well delivered version of this song. Jerry's vocals are strong and Keith is adding some very nice honky-tonk piano!",
      "archive_url": "https://headyversion.com/show/1134/archive/"
    },
    {
      "votes": 1,
      "date": "1972-07-21",
      "show_id": 1411,
      "venue": "Paramount Northwest Theater Seattle, WA",
      "description": "Are there better versions out there? Undoubtedly! But this is still worthy of an entry.  Some nice, tinkling piano.",
      "archive_url": "https://headyversion.com/show/1411/archive/"
    },
    {
      "votes": 1,
      "date": "1984-10-11",
      "show_id": 1708,
      "venue": "Civic Center Augusta, ME",
      "description": "Such a strong version. I love jers raspy voice belting this one out",
      "archive_url": "https://headyversion.com/show/1708/archive/"
    },
    {
      "votes": 1,
      "date": "1994-06-17",
      "show_id": 255,
      "venue": "Autzen Stadium - University of Oregon Eugene, OR",
      "description": "Pretty good version, Jerry's guitar goes out for part of the jam and Vince has an opportunity to shine, but is timid instead and energy level drops.",
      "archive_url": "https://headyversion.com/show/255/archive/"
    },
    {
      "votes": 1,
      "date": "1980-06-07",
      "show_id": 1958,
      "venue": "Folsom Field Boulder, CO",
      "description": "Jerry means every note in this solo. Love the false harmonics and power chords.",
      "archive_url": "https://headyversion.com/show/1958/archive/"
    },
    {
      "votes": 1,
      "date": "1988-09-24",
      "show_id": 1339,
      "venue": "Madison Square Garden New York, NY",
      "description": "Might not be the best but it should be on here somewhere. A nice 88 version always love brent on this song",
      "archive_url": "https://headyversion.com/show/1339/archive/"
    },
    {
      "votes": 1,
      "date": "1983-08-27",
      "show_id": 73,
      "venue": "Seattle Center Coliseum Seattle, WA",
      "description": "Does Jerry totally botch a verse? Yes. Does the solo/rest of the song make up for it? Definitely.",
      "archive_url": "https://headyversion.com/show/73/archive/"
    },
    {
      "votes": 1,
      "date": "1986-07-06",
      "show_id": 2010,
      "venue": "RFK Stadium Washington, DC",
      "description": "",
      "archive_url": "https://headyversion.com/show/2010/archive/"
    },
    {
      "votes": 1,
      "date": "1986-07-07",
      "show_id": 1098,
      "venue": "RFK Stadium Washington, DC",
      "description": "",
      "archive_url": "https://headyversion.com/show/1098/archive/"
    },
    {
      "votes": 1,
      "date": "1972-07-18",
      "show_id": 461,
      "venue": "Rossevelt Stadium Jersey City, NJ",
      "description": "Rambling right along in this three-set marathon",
      "archive_url": "https://headyversion.com/show/461/archive/"
    },
    {
      "votes": 1,
      "date": "1989-12-28",
      "show_id": 1195,
      "venue": "Coliseum Arean Oakland, CA",
      "description": "Really soulful take. Jerry's voice, although slightly ragged, does everything he wants it to do.",
      "archive_url": "https://headyversion.com/show/1195/archive/"
    },
    {
      "votes": 1,
      "date": "1989-04-09",
      "show_id": 1295,
      "venue": "Freedom Hall Louisville, KY",
      "description": "kinetic  aries version from a heavyweight year",
      "archive_url": "https://headyversion.com/show/1295/archive/"
    },
    {
      "votes": 1,
      "date": "1982-04-18",
      "show_id": 514,
      "venue": "Hartford Civic Center Hartford, CT",
      "description": "welcome wink of a heel-diggingly true pure rendering. Spiky and down home like jerry and hunter's best evocations of timeless tribulation and delitez.",
      "archive_url": "https://headyversion.com/show/514/archive/"
    },
    {
      "votes": 1,
      "date": "1989-10-22",
      "show_id": 1554,
      "venue": "Charlotte Coliseum Charlotte, NC",
      "description": "Sparkling rendition. Fans of upbeat '89 versions like 7/7 should check this out.",
      "archive_url": "https://headyversion.com/show/1554/archive/"
    },
    {
      "votes": 1,
      "date": "1988-07-31",
      "show_id": 1884,
      "venue": "Laguna Seca Recreation Area Monterey, CA",
      "description": "What you can expect from 88. Good performance.",
      "archive_url": "https://headyversion.com/show/1884/archive/"
    },
    {
      "votes": 1,
      "date": "1990-06-15",
      "show_id": 264,
      "venue": "Shoreline Amphitheatre Mountain View, CA",
      "description": "Note for note, I still haven't found a live Ramble on Rose with such a perfect solo. My 'go to' Ramble, always has been.",
      "archive_url": "https://headyversion.com/show/264/archive/"
    },
    {
      "votes": 1,
      "date": "1990-10-17",
      "show_id": 1695,
      "venue": "Grugahalle Essen,",
      "description": "Grugahalle, Essen - I know this song ain\u2019t ever gonna end",
      "archive_url": "https://headyversion.com/show/1695/archive/"
    },
    {
      "votes": 1,
      "date": "1987-09-22",
      "show_id": 1410,
      "venue": "The Spectrum Philadelphia, PA",
      "description": "very strong RoR from the second golden era",
      "archive_url": "https://headyversion.com/show/1410/archive/"
    },
    {
      "votes": 1,
      "date": "1971-11-07",
      "show_id": 567,
      "venue": "Harding Theatre San Francisco, CA",
      "description": "Pretty underrated show overall.",
      "archive_url": "https://headyversion.com/show/567/archive/"
    },
    {
      "votes": 1,
      "date": "1973-11-20",
      "show_id": 1071,
      "venue": "Denver Coliseum Denver, CO",
      "description": "classic",
      "archive_url": "https://headyversion.com/show/1071/archive/"
    },
    {
      "votes": 1,
      "date": "1972-09-23",
      "show_id": 270,
      "venue": "Palace Theater Waterbury, CT",
      "description": "Insanely strong version inexplicably absent til now. Check out Garcia's guitar run into the \"just like crazy Otto\" line & you'll be ready to upvote!",
      "archive_url": "https://headyversion.com/show/270/archive/"
    }
  ]
}