{
  "song_id": 340,
  "name": "Believe It Or Not",
  "performances": [
    {
      "votes": 29,
      "date": "1990-03-22",
      "show_id": 565,
      "venue": "Copps Coliseum Hamilton, ON",
      "description": "There are a couple versions that people generally argue for, but this one is and always will be my favorite.",
      "archive_url": "https://headyversion.com/show/565/archive/"
    },
    {
      "votes": 16,
      "date": "1988-06-23",
      "show_id": 871,
      "venue": "Alpine Valley Music Theatre East Troy, WI",
      "description": "The first live version needs to be on this list, very well sung by Garcia and well played. They didn\u2019t play this song enough.",
      "archive_url": "https://headyversion.com/show/871/archive/"
    },
    {
      "votes": 11,
      "date": "1988-07-29",
      "show_id": 327,
      "venue": "Laguna Seca Recreation Area Monterey, CA",
      "description": "Jerry rips a sweet solo in the middle of this one.  Emotive closing lyrics",
      "archive_url": "https://headyversion.com/show/327/archive/"
    },
    {
      "votes": 10,
      "date": "1988-06-30",
      "show_id": 271,
      "venue": "Silver Stadium Rochester, NY",
      "description": "This is a good version and I really like the tone on Garcia\u2019s guitar during the solo and great closing vocals.  Give it a listen.",
      "archive_url": "https://headyversion.com/show/271/archive/"
    },
    {
      "votes": 7,
      "date": "1988-07-17",
      "show_id": 56,
      "venue": "Greek Theater - University of California Berkeley, CA",
      "description": "A good version of this underrated song.",
      "archive_url": "https://headyversion.com/show/56/archive/"
    },
    {
      "votes": 6,
      "date": "1988-10-21",
      "show_id": 1016,
      "venue": "Reunion Arena Dallas, TX",
      "description": "A cool version from a great show.",
      "archive_url": "https://headyversion.com/show/1016/archive/"
    },
    {
      "votes": 3,
      "date": "1988-06-01",
      "show_id": 1044,
      "venue": "Studio-Inn By The Sea Tape Cape Elizabeth, ME",
      "description": "Part of the Inn BY The Sea tapes. These tape are full of kool nuggets!",
      "archive_url": "https://headyversion.com/show/1044/archive/"
    },
    {
      "votes": 3,
      "date": "1988-07-02",
      "show_id": 324,
      "venue": "Oxford Plains Speedway Oxford, ME",
      "description": "Well it used to be on this date until mr bean and his brain dump gangstalking cronies moved it. Mind reading folks. What a gonna do. Mr bean is a thie",
      "archive_url": "https://headyversion.com/show/324/archive/"
    },
    {
      "votes": 1,
      "date": "1988-09-09",
      "show_id": 1993,
      "venue": "The Spectrum Philadelphia, PA",
      "description": "Fine, soulful performance. Garcia sings \"in a world time forgot\" instead of \"that guitars never caught.\" Alternate lyric they maybe wanted to put.",
      "archive_url": "https://headyversion.com/show/1993/archive/"
    }
  ]
}